{
  "$schema": "https://mintlify.com/docs.json",
  "name": "Shadcn Admin",
  "theme": "mint",
  "colors": {
    "primary": "#040404",
    "light": "#040404",
    "dark": "#040404"
  },
  "navbar": {
    "primary": {
      "type": "github",
      "href": "https://github.com/satnaing/shadcn-admin"
    }
  },
  "footer": {
    "socials": {
      "github": "https://github.com/satnaing/shadcn-admin"
    }
  },
  "navigation": {
    "tabs": [
      {
        "tab": "Documentation",
        "groups": [
          {
            "group": "Get Started",
            "pages": [
              "introduction",
              "installation",
              "quickstart"
            ]
          },
          {
            "group": "Core Concepts",
            "pages": [
              "concepts/project-structure",
              "concepts/routing",
              "concepts/theming",
              "concepts/rtl-support"
            ]
          },
          {
            "group": "Features",
            "pages": [
              "features/sidebar",
              "features/layouts",
              "features/data-tables",
              "features/authentication",
              "features/global-search",
              "features/dark-mode"
            ]
          },
          {
            "group": "Customization",
            "pages": [
              "customization/layout-options",
              "customization/theme-configuration",
              "customization/adding-pages",
              "customization/custom-components"
            ]
          },
          {
            "group": "Pages",
            "pages": [
              "pages/dashboard",
              "pages/tasks",
              "pages/users",
              "pages/chats",
              "pages/apps",
              "pages/settings",
              "pages/error-pages"
            ]
          }
        ]
      },
      {
        "tab": "Components",
        "groups": [
          {
            "group": "Overview",
            "pages": [
              "components/overview"
            ]
          },
          {
            "group": "Layout Components",
            "pages": [
              "components/app-sidebar",
              "components/header",
              "components/main-layout"
            ]
          },
          {
            "group": "Custom Components",
            "pages": [
              "components/command-menu",
              "components/config-drawer",
              "components/data-table",
              "components/date-picker",
              "components/password-input",
              "components/theme-switch"
            ]
          },
          {
            "group": "UI Components",
            "pages": [
              "components/ui-components"
            ]
          }
        ]
      },
      {
        "tab": "Guides",
        "groups": [
          {
            "group": "Development",
            "pages": [
              "guides/local-development",
              "guides/building-production",
              "guides/deploying"
            ]
          },
          {
            "group": "Integration",
            "pages": [
              "guides/clerk-integration",
              "guides/api-integration",
              "guides/state-management"
            ]
          },
          {
            "group": "Advanced",
            "pages": [
              "guides/rtl-implementation",
              "guides/updating-components",
              "guides/performance-optimization"
            ]
          }
        ]
      }
    ]
  }
}
